.testr.conf
AUTHORS
ChangeLog
README.rst
requirements.txt
setup.cfg
setup.py
test-requirements.txt
examples/deployment.json
salt_mc.egg-info/PKG-INFO
salt_mc.egg-info/SOURCES.txt
salt_mc.egg-info/dependency_links.txt
salt_mc.egg-info/entry_points.txt
salt_mc.egg-info/not-zip-safe
salt_mc.egg-info/requires.txt
salt_mc.egg-info/top_level.txt
saltmc/__init__.py
saltmc/config.py
saltmc/download.py
saltmc/exceptions.py
saltmc/link.py
saltmc/shell.py
saltmc/sync.py
saltmc/utils.py
saltmc/cli/__init__.py
saltmc/cli/status.py
saltmc/cli/sync.py
saltmc/fetchers/__init__.py
saltmc/fetchers/impl_git.py
saltmc/fetchers/impl_requests.py
saltmc/tests/__init__.py
saltmc/tests/test_link.py