Metadata-Version: 1.1
Name: salt-mc
Version: 0.0.1.8.g2ea131c
Summary: Tool to help you manage a salt deployment.
Home-page: ...
Author: Endre Karlson
Author-email: endre.karlson@hp.com
License: UNKNOWN
Platform: UNKNOWN
Classifier: Intended Audience :: Information Technology
Classifier: Intended Audience :: System Administrators
Classifier: License :: OSI Approved :: Apache Software License
Classifier: Operating System :: POSIX :: Linux
Classifier: Programming Language :: Python
Classifier: Programming Language :: Python :: 2
Classifier: Programming Language :: Python :: 2.7
Classifier: Programming Language :: Python :: 2.6
